<?xml version="1.0"?>
<AssetList xmlns:xsi="http://www.w3.org/2001/XMLSchema-instance" xmlns:xsd="http://www.w3.org/2001/XMLSchema">
  <list>
    <AssetItem>
      <DLLName>InterRules, Version=1.0.0.0, Culture=neutral, PublicKeyToken=null</DLLName>
      <names>
        <NameAndTypeName>
          <name>Starwar1</name>
          <typeNames>InterRules.Starwar.StarwarRule</typeNames>
        </NameAndTypeName>
        <NameAndTypeName>
          <name>Starwar2</name>
          <typeNames>InterRules.Starwar.StarwarRule2</typeNames>
        </NameAndTypeName>
      </names>
    </AssetItem>
  </list>
</AssetList>